mehdi_test/__init__.py
mehdi_test/mehdi_test.py
src/__init__.py
src/utils.py
tests/__init__.py
tests/test_mehdi_test.py
mehdi_test-0.1.5.dist-info/AUTHORS.rst
mehdi_test-0.1.5.dist-info/LICENSE
mehdi_test-0.1.5.dist-info/METADATA
mehdi_test-0.1.5.dist-info/WHEEL
mehdi_test-0.1.5.dist-info/top_level.txt
mehdi_test-0.1.5.dist-info/RECORD
