Metadata-Version: 2.1
Name: mehdi_test
Version: 0.1.5
Summary: A brief description of your package
Home-page: https://github.com/Hamzeluie/your_project
Author: Mehdi Hamzeluie
Author-email: mehdihamze73@gmail.com
License: MIT
Classifier: Programming Language :: Python :: 3
Classifier: License :: OSI Approved :: MIT License
Classifier: Operating System :: OS Independent
Requires-Python: >=3.6
License-File: LICENSE
License-File: AUTHORS.rst
Requires-Dist: numpy
Requires-Dist: pandas
